carb_optimizer/__init__.py
carb_optimizer/adapters/__init__.py
carb_optimizer/adapters/base.py
carb_optimizer/adapters/carbon_encoded_order.py
carb_optimizer/adapters/carbonv1.py
carb_optimizer/adapters/generic.py
carb_optimizer/adapters/token.py
carb_optimizer/adapters/univ2.py
carb_optimizer/adapters/univ3.py
carb_optimizer/analyzer.py
carb_optimizer/arbgraphs.py
carb_optimizer/curves/__init__.py
carb_optimizer/curves/cpc.py
carb_optimizer/curves/cpcinverter.py
carb_optimizer/curves/curvebase.py
carb_optimizer/curves/curvecontainer.py
carb_optimizer/curves/edgecontainer.py
carb_optimizer/curves/params.py
carb_optimizer/curves/simplepair.py
carb_optimizer/curves/tokenscale.py
carb_optimizer/enums/__init__.py
carb_optimizer/enums/exchange_type.py
carb_optimizer/graphs/__init__.py
carb_optimizer/graphs/base.py
carb_optimizer/graphs/curvegraph.py
carb_optimizer/graphs/pairgraph.py
carb_optimizer/helpers/__init__.py
carb_optimizer/helpers/attrdict.py
carb_optimizer/helpers/cryptocompare.py
carb_optimizer/helpers/dcbase.py
carb_optimizer/helpers/noneresult.py
carb_optimizer/helpers/symbol_lookup.py
carb_optimizer/helpers/timer.py
carb_optimizer/interactive.py
carb_optimizer/invariants/README.md
carb_optimizer/invariants/__init__.py
carb_optimizer/invariants/bancor.py
carb_optimizer/invariants/functions/__init__.py
carb_optimizer/invariants/functions/core.py
carb_optimizer/invariants/functions/funcs.py
carb_optimizer/invariants/functions/funcsAMM.py
carb_optimizer/invariants/invariant.py
carb_optimizer/invariants/kernel.py
carb_optimizer/invariants/solidly.py
carb_optimizer/invariants/vector.py
carb_optimizer/optimizer/__init__.py
carb_optimizer/optimizer/arboptimizerbase.py
carb_optimizer/optimizer/base.py
carb_optimizer/optimizer/convexoptimizer.py
carb_optimizer/optimizer/graphoptimizer.py
carb_optimizer/optimizer/margpfulloptimizer.py
carb_optimizer/optimizer/margppairoptimizer.py
carb_optimizer/releaseinfo/__init__.py
carb_optimizer/releaseinfo/release_number.py
carb_optimizer-0.0.53.dist-info/LICENSE
carb_optimizer-0.0.53.dist-info/METADATA
carb_optimizer-0.0.53.dist-info/WHEEL
carb_optimizer-0.0.53.dist-info/RECORD
