Metadata-Version: 2.1
Name: carb-optimizer
Version: 0.0.53
Summary: 
License: MIT
Author: Bancor Network
Author-email: services@bancor.network
Requires-Python: >=3.11,<4.0
Classifier: License :: OSI Approved :: MIT License
Classifier: Programming Language :: Python :: 3
Classifier: Programming Language :: Python :: 3.11
Classifier: Programming Language :: Python :: 3.12
Requires-Dist: click (>=8.1.7,<9.0.0)
Requires-Dist: cvxpy (>=1.3.1,<2.0.0)
Requires-Dist: matplotlib (>=3.7.1,<4.0.0)
Requires-Dist: networkx (>=3.3,<4.0)
Requires-Dist: pandas (>=1.5.2,<2.0.0)
Requires-Dist: scipy (>=1.7.3,<2.0.0)
